azure/mgmt/managementgroups/__init__.py
azure/mgmt/managementgroups/management_groups_api.py
azure/mgmt/managementgroups/version.py
azure/mgmt/managementgroups/models/__init__.py
azure/mgmt/managementgroups/models/check_name_availability_request.py
azure/mgmt/managementgroups/models/check_name_availability_request_py3.py
azure/mgmt/managementgroups/models/check_name_availability_result.py
azure/mgmt/managementgroups/models/check_name_availability_result_py3.py
azure/mgmt/managementgroups/models/create_management_group_child_info.py
azure/mgmt/managementgroups/models/create_management_group_child_info_py3.py
azure/mgmt/managementgroups/models/create_management_group_details.py
azure/mgmt/managementgroups/models/create_management_group_details_py3.py
azure/mgmt/managementgroups/models/create_management_group_request.py
azure/mgmt/managementgroups/models/create_management_group_request_py3.py
azure/mgmt/managementgroups/models/create_parent_group_info.py
azure/mgmt/managementgroups/models/create_parent_group_info_py3.py
azure/mgmt/managementgroups/models/entity_hierarchy_item.py
azure/mgmt/managementgroups/models/entity_hierarchy_item_py3.py
azure/mgmt/managementgroups/models/entity_info.py
azure/mgmt/managementgroups/models/entity_info_paged.py
azure/mgmt/managementgroups/models/entity_info_py3.py
azure/mgmt/managementgroups/models/entity_parent_group_info.py
azure/mgmt/managementgroups/models/entity_parent_group_info_py3.py
azure/mgmt/managementgroups/models/error_details.py
azure/mgmt/managementgroups/models/error_details_py3.py
azure/mgmt/managementgroups/models/error_response.py
azure/mgmt/managementgroups/models/error_response_py3.py
azure/mgmt/managementgroups/models/management_group.py
azure/mgmt/managementgroups/models/management_group_child_info.py
azure/mgmt/managementgroups/models/management_group_child_info_py3.py
azure/mgmt/managementgroups/models/management_group_details.py
azure_mgmt_managementgroups-0.1.0.dist-info/METADATA
azure_mgmt_managementgroups-0.1.0.dist-info/RECORD
azure_mgmt_managementgroups-0.1.0.dist-info/WHEEL
azure_mgmt_managementgroups-0.1.0.dist-info/top_level.txt
